[
  {
    "id": "1",
    "image": "http://www.example.com/",
    "title": "Pulsa RP 5.000",
    "point": "4470 points"
  },
  {
    "id": "2",
    "image": "http://www.example.com/",
    "title": "Pulsa RP 5.000",
    "point": "4470 points"
  },
  {
    "id": "3",
    "image": "http://www.example.com/",
    "title": "Pulsa RP 5.000",
    "point": "4470 points"
  },
  {
    "id": "4",
    "image": "http://www.example.com/",
    "title": "Pulsa RP 5.000",
    "point": "4470 points"
  },
  {
    "id": "5",
    "image": "http://www.example.com/",
    "title": "Pulsa RP 5.000",
    "point": "4470 points"
  }
]
